{
    "nodes": [
        {
            "id": "surgery_clinic",
            "x": 0,
            "y": 0,
            "type": "main",
            "name": "外科诊室",
            "description": "处理需手术或操作的外伤、感染、肿瘤等体表及内部疾病，进行术前评估与术后复查。"
        },
        {
            "id": "crossroad1",
            "x": 1,
            "y": 0,
            "type": "nav"
        },
        {
            "id": "crossroad2",
            "x": 1,
            "y": 1,
            "type": "nav"
        },
        {
            "id": "emergency_clinic",
            "x": 2,
            "y": 1,
            "type": "main",
            "name": "急诊室",
            "description": "24小时开放，专门用于抢救与处理突发、危重的伤病员，如严重外伤、大出血、休克、急性腹痛等。"
        },
        {
            "id": "internal_clinic",
            "x": 0,
            "y": 2,
            "type": "main",
            "name": "内科诊室",
            "description": "通过问诊、查体及非手术方式（如药物），诊疗人体内部各系统疾病，如心脑血管、呼吸、消化、内分泌等疾病。"
        },
        {
            "id": "crossroad3",
            "x": 1,
            "y": 2,
            "type": "nav"
        },
        {
            "id": "pediatric_clinic",
            "x": 0,
            "y": 3,
            "type": "main",
            "name": "儿科诊室",
            "description": "专门为14周岁以下儿童及青少年提供疾病诊疗、健康检查与生长发育评估，环境与用药剂量均有别于成人。"
        },
        {
            "id": "crossroad4",
            "x": 1,
            "y": 3,
            "type": "nav"
        },
        {
            "id": "toilet",
            "x": 4,
            "y": 3,
            "type": "main",
            "name": "洗手间",
            "description": "为患者、家属及医护人员提供必要的卫生设施，保障院内基本卫生需求与个人隐私。"
        },
        {
            "id": "registration_center",
            "x": 0,
            "y": 4,
            "type": "main",
            "name": "挂号中心",
            "description": "患者就医第一站，负责登记个人信息、安排就诊科室与医生，并生成病历号，是分流患者、组织诊疗流程的核心。"
        },
        {
            "id": "quit",
            "x": -1,
            "y": 5,
            "type": "main",
            "name": "出口",
            "description": "离开医院的出口。"
        },
        {
            "id": "crossroad5",
            "x": 0,
            "y": 5,
            "type": "nav"
        },
        {
            "id": "crossroad6",
            "x": 1,
            "y": 5,
            "type": "nav"
        },
        {
            "id": "crossroad7",
            "x": 2,
            "y": 5,
            "type": "nav"
        },
        {
            "id": "payment_center",
            "x": 3,
            "y": 5,
            "type": "main",
            "name": "缴费处",
            "description": "处理门急诊、住院等各项医疗费用的收款、结算业务，支持多种支付方式，是医院财务流程的关键环节。"
        },
        {
            "id": "entrance",
            "x": 0,
            "y": 6,
            "type": "main",
            "name": "入口",
            "description": "医院主入口。"
        },
        {
            "id": "pharmacy",
            "x": 2,
            "y": 6,
            "type": "main",
            "name": "药房",
            "description": "依据医生处方为患者调配、发放药品，并提供用药咨询与指导，确保患者安全、正确地使用药物。"
        }
    ],
    "edges": [
        {
            "u": "surgery_clinic",
            "v": "crossroad1",
            "name": "北翼走廊"
        },
        {
            "u": "crossroad1",
            "v": "crossroad2",
            "name": "中心纵向走廊"
        },
        {
            "u": "crossroad2",
            "v": "emergency_clinic",
            "name": "急诊通道"
        },
        {
            "u": "crossroad2",
            "v": "crossroad3",
            "name": "中心纵向走廊"
        },
        {
            "u": "internal_clinic",
            "v": "crossroad3",
            "name": "内科通道"
        },
        {
            "u": "crossroad3",
            "v": "crossroad4",
            "name": "中心纵向走廊"
        },
        {
            "u": "crossroad4",
            "v": "pediatric_clinic",
            "name": "儿科通道"
        },
        {
            "u": "crossroad4",
            "v": "toilet",
            "name": "公用走廊"
        },
        {
            "u": "crossroad4",
            "v": "crossroad5",
            "name": "中心纵向走廊"
        },
        {
            "u": "registration_center",
            "v": "crossroad5",
            "name": "大厅通道"
        },
        {
            "u": "quit",
            "v": "crossroad5",
            "name": "大厅通道"
        },
        {
            "u": "crossroad5",
            "v": "crossroad6",
            "name": "横向主走廊"
        },
        {
            "u": "crossroad6",
            "v": "crossroad7",
            "name": "横向主走廊"
        },
        {
            "u": "crossroad7",
            "v": "payment_center",
            "name": "财务区通道"
        },
        {
            "u": "entrance",
            "v": "crossroad5",
            "name": "大厅通道"
        },
        {
            "u": "pharmacy",
            "v": "crossroad7",
            "name": "取药通道"
        }
    ]
}